gradupe/__init__.py
gradupe/__main__.py
gradupe/cli.py
gradupe/lib.py
gradupe-3.0.5.dist-info/entry_points.txt
gradupe-3.0.5.dist-info/licenses/LICENSE
gradupe-3.0.5.dist-info/WHEEL
gradupe-3.0.5.dist-info/METADATA
gradupe-3.0.5.dist-info/RECORD
