Metadata-Version: 2.4
Name: gradupe
Version: 3.0.5
Summary: Sobel Gradient Image Deduplication
Keywords: image-dedupe,sobel-gradient
Author-email: David <wavim.wu@gmail.com>
Requires-Python: >=3.11
License-Expression: MIT
Classifier: Development Status :: 5 - Production/Stable
Classifier: Environment :: Console
Classifier: Intended Audience :: End Users/Desktop
Classifier: Intended Audience :: Science/Research
Classifier: Natural Language :: English
Classifier: Operating System :: OS Independent
Classifier: Programming Language :: Python
Classifier: Programming Language :: Python :: 3
Classifier: Programming Language :: Python :: 3 :: Only
Classifier: Programming Language :: Python :: 3.11
Classifier: Programming Language :: Python :: 3.12
Classifier: Programming Language :: Python :: 3.13
Classifier: Programming Language :: Python :: 3.14
Classifier: Topic :: Scientific/Engineering :: Image Processing
Classifier: Typing :: Typed
License-File: LICENSE
Requires-Dist: numba >=0.63.1,<0.64.0
Requires-Dist: numpy >=2.3.5,<2.4.0
Requires-Dist: opencv-python-headless >=4.13.0,<5.0.0
Requires-Dist: typer >=0.21.1,<0.22.0
Project-URL: Repository, https://github.com/wavim/gradupe
